CHANGELOG.txt
LICENCE.txt
MANIFEST.in
README.txt
setup.py
Pubsam/__init__.py
Pubsam/example.py
Pubsam.egg-info/PKG-INFO
Pubsam.egg-info/SOURCES.txt
Pubsam.egg-info/dependency_links.txt
Pubsam.egg-info/entry_points.txt
Pubsam.egg-info/requires.txt
Pubsam.egg-info/top_level.txt